turing_21_matrix_operations/__init__.py
turing_21_matrix_operations/main.py
turing_21_matrix_operations-0.1.5.dist-info/METADATA
turing_21_matrix_operations-0.1.5.dist-info/WHEEL
turing_21_matrix_operations-0.1.5.dist-info/RECORD
