Metadata-Version: 2.1
Name: turing_21_matrix_operations
Version: 0.1.5
Summary: Turing college DE 2.1 coursework for Matrix operations: transform, window and cross-correlation using Python standard library.
Author: Domantas G
Requires-Python: >=3.10,<3.13
Classifier: Programming Language :: Python :: 3
Classifier: Programming Language :: Python :: 3.10
Classifier: Programming Language :: Python :: 3.11
Requires-Dist: numpy (>=1.26.1,<2.0.0)
